lanim/__main__.py
lanim/core.py
lanim/easings.py
lanim/examples/hello.py
lanim/examples/showcase.py
lanim/latex.py
lanim/pil.py
lanim/pil_graphics.py
lanim/pil_machinery.py
lanim/pil_types.py
lanim/pil_utils.py
lanim/py.typed
lanim/standalone.py
lanim/threaded_cache.py
lanim-0.3.1.dist-info/LICENSE
lanim-0.3.1.dist-info/WHEEL
lanim-0.3.1.dist-info/METADATA
lanim-0.3.1.dist-info/RECORD
