Metadata-Version: 2.1
Name: lanim
Version: 0.3.1
Summary: Functional animation library
Home-page: https://github.com/decorator-factory/lanim
License: MIT
Author: decorator-factory
Author-email: 42166884+decorator-factory@users.noreply.github.com
Requires-Python: >=3.9,<4.0
Classifier: Development Status :: 2 - Pre-Alpha
Classifier: License :: OSI Approved :: MIT License
Classifier: Programming Language :: Python :: 3
Classifier: Programming Language :: Python :: 3.9
Classifier: Topic :: Multimedia
Requires-Dist: pillow (>=8.3.2,<9.0.0)
